{
  "$schema": "https://developer.microsoft.com/json-schemas/fabric/item/report/definition/visualContainer/2.7.0/schema.json",
  "name": "e1c72d92778c8d0f23d3",
  "position": {
    "x": 959.57446808510645,
    "y": 1002.1276595744681,
    "z": 25000,
    "height": 298.936170212766,
    "width": 959.57446808510645,
    "tabOrder": 25000
  },
  "visual": {
    "visualType": "textbox",
    "objects": {
      "general": [
        {
          "properties": {
            "paragraphs": [
              {
                "textRuns": [
                  {
                    "value": "Recomendações e Insights",
                    "textStyle": {
                      "fontFamily": "Segoe UI Semibold",
                      "fontSize": "14pt",
                      "color": "#808080"
                    }
                  }
                ],
                "horizontalTextAlignment": "center"
              },
              {
                "textRuns": [
                  {
                    "value": ""
                  }
                ]
              },
              {
                "textRuns": [
                  {
                    "value": ""
                  }
                ]
              },
              {
                "textRuns": [
                  {
                    "value": "\t",
                    "textStyle": {
                      "color": "#808080"
                    }
                  },
                  {
                    "value": "🚚 LOGÍSTICA - Lead time no Norte/NE é 3x maior que SP. Atraso derruba nota de 4.3 para 2.6.",
                    "textStyle": {
                      "fontFamily": "Segoe UI Semibold",
                      "fontSize": "14pt",
                      "color": "#808080"
                    }
                  }
                ]
              },
              {
                "textRuns": [
                  {
                    "value": "\t",
                    "textStyle": {
                      "color": "#808080"
                    }
                  },
                  {
                    "value": "→ CDs regionais e parcerias logísticas locais",
                    "textStyle": {
                      "fontFamily": "Segoe UI Semibold",
                      "fontSize": "14pt",
                      "color": "#808080"
                    }
                  }
                ]
              },
              {
                "textRuns": [
                  {
                    "value": ""
                  }
                ]
              },
              {
                "textRuns": [
                  {
                    "value": "\t",
                    "textStyle": {
                      "color": "#808080"
                    }
                  },
                  {
                    "value": "⭐ SELLERS - Top 10 sellers concentram grande parte da receita. Sellers ruins derrubam NPS geral.",
                    "textStyle": {
                      "fontFamily": "Segoe UI Semibold",
                      "fontSize": "14pt",
                      "color": "#808080"
                    }
                  }
                ]
              },
              {
                "textRuns": [
                  {
                    "value": "\t",
                    "textStyle": {
                      "color": "#808080"
                    }
                  },
                  {
                    "value": "→ Programa de classificação  e curadoria por qualidade",
                    "textStyle": {
                      "fontFamily": "Segoe UI Semibold",
                      "fontSize": "14pt",
                      "color": "#808080"
                    }
                  }
                ]
              },
              {
                "textRuns": [
                  {
                    "value": ""
                  }
                ]
              },
              {
                "textRuns": [
                  {
                    "value": "\t",
                    "textStyle": {
                      "color": "#808080"
                    }
                  },
                  {
                    "value": "🔄 RETENÇÃO/FIDELIZAÇÃO - 97% dos clientes não voltam. Recompra = 2.9%.",
                    "textStyle": {
                      "fontFamily": "Segoe UI Semibold",
                      "fontSize": "14pt",
                      "color": "#808080"
                    }
                  }
                ]
              },
              {
                "textRuns": [
                  {
                    "value": "\t",
                    "textStyle": {
                      "color": "#808080"
                    }
                  },
                  {
                    "value": "→ Programa de fidelidade e cupons pós-primeira compra",
                    "textStyle": {
                      "fontFamily": "Segoe UI Semibold",
                      "fontSize": "14pt",
                      "color": "#808080"
                    }
                  }
                ]
              }
            ]
          }
        }
      ]
    },
    "visualContainerObjects": {
      "background": [
        {
          "properties": {
            "transparency": {
              "expr": {
                "Literal": {
                  "Value": "100D"
                }
              }
            }
          }
        }
      ],
      "border": [
        {
          "properties": {
            "show": {
              "expr": {
                "Literal": {
                  "Value": "true"
                }
              }
            },
            "color": {
              "solid": {
                "color": {
                  "expr": {
                    "ThemeDataColor": {
                      "ColorId": 0,
                      "Percent": -0.1
                    }
                  }
                }
              }
            }
          }
        }
      ]
    },
    "drillFilterOtherVisuals": true
  }
}